{
    "metadata": {
        "media_type": "movie",
        "title": "Happy Gilmore",
        "director": "Dennis Dugan",
        "release_year": 1996,
        "genres": [
            "Comedy",
            "Sport"
        ],
        "top_billed_actors": [
            "Adam Sandler",
            "Christopher McDonald",
            "Julie Bowen"
        ],
        "criteria_grades": {
            "Storytelling": 0,
            "Character Development": 0,
            "Visual Presentation": 0
        }
    },
    "content": {
        "short_description": "A rejected hockey player puts his skills to the golf course to save his grandmother's house.",
        "quotes": [],
        "notes": "Favorite Scenes, Favorite Lines"
    }
}